PORTify.py
libs/__init__.py
libs/firewall.py
libs/platforms.py
libs/spotipy.py
portify_knocker-0.1.0.dist-info/licenses/LICENSE
portify_knocker-0.1.0.dist-info/METADATA
portify_knocker-0.1.0.dist-info/WHEEL
portify_knocker-0.1.0.dist-info/entry_points.txt
portify_knocker-0.1.0.dist-info/top_level.txt
portify_knocker-0.1.0.dist-info/RECORD
