Metadata-Version: 2.4
Name: PORTify-knocker
Version: 0.1.0
Summary: Open and close firewall ports using Spotify's current played track
Author-email: LavaTime <amitkeren9@gmail.com>
Keywords: spotify,port,knocking,firewall,open,close,song,track,playing
Classifier: Development Status :: 3 - Alpha
Classifier: Programming Language :: Python
Requires-Python: >3.8
License-File: LICENSE
Requires-Dist: spotipy
Requires-Dist: typing_extensions
Requires-Dist: pydantic
Requires-Dist: pydantic_settings
Requires-Dist: setuptools
Dynamic: license-file
